pytest_elasticsearch/__init__.py
pytest_elasticsearch/config.py
pytest_elasticsearch/executor.py
pytest_elasticsearch/factories.py
pytest_elasticsearch/plugin.py
pytest_elasticsearch/py.typed
pytest_elasticsearch_test-0.0.3.dist-info/licenses/AUTHORS.rst
pytest_elasticsearch_test-0.0.3.dist-info/licenses/COPYING
pytest_elasticsearch_test-0.0.3.dist-info/licenses/COPYING.lesser
pytest_elasticsearch_test-0.0.3.dist-info/METADATA
pytest_elasticsearch_test-0.0.3.dist-info/WHEEL
pytest_elasticsearch_test-0.0.3.dist-info/entry_points.txt
pytest_elasticsearch_test-0.0.3.dist-info/top_level.txt
pytest_elasticsearch_test-0.0.3.dist-info/zip-safe
pytest_elasticsearch_test-0.0.3.dist-info/RECORD
