Metadata-Version: 2.4
Name: pytest-elasticsearch-test
Version: 0.0.3
Summary: Elasticsearch fixtures and fixture factories for Pytest.
Author-email: Grzegorz Śliwiński <fizyk+pypi@fizyk.dev>
Project-URL: Source, https://github.com/ClearcodeHQ/pytest-elasticsearch
Project-URL: Bug Tracker, https://github.com/ClearcodeHQ/pytest-elasticsearch/issues
Project-URL: Changelog, https://github.com/ClearcodeHQ/pytest-elasticsearch/blob/v0.0.3/CHANGES.rst
Keywords: tests,pytest,fixture,elasticsearch
Classifier: Development Status :: 5 - Production/Stable
Classifier: Environment :: Web Environment
Classifier: Intended Audience :: Developers
Classifier: License :: OSI Approved :: GNU Lesser General Public License v3 or later (LGPLv3+)
Classifier: Natural Language :: English
Classifier: Operating System :: OS Independent
Classifier: Programming Language :: Python
Classifier: Programming Language :: Python :: 3
Classifier: Programming Language :: Python :: 3.8
Classifier: Programming Language :: Python :: 3.9
Classifier: Programming Language :: Python :: 3.10
Classifier: Programming Language :: Python :: 3.11
Classifier: Programming Language :: Python :: 3.12
Classifier: Programming Language :: Python :: 3 :: Only
Classifier: Topic :: Software Development :: Libraries :: Python Modules
Classifier: Topic :: Software Development :: Testing
Classifier: Framework :: Pytest
Requires-Python: >=3.8
License-File: COPYING
License-File: COPYING.lesser
License-File: AUTHORS.rst
Requires-Dist: pytest>=7.0
Requires-Dist: port-for>=0.7.1
Requires-Dist: mirakuru
Requires-Dist: elasticsearch>=7
Dynamic: license-file
